[
  {
    "id": "I-001",
    "level": "intermediate",
    "category": "conditionals",
    "xpReward": 40,
    "difficulty": 3,
    "name": "First Conditional",
    "explanation": "Used for real and possible future situations. Exams test tense sequence errors in if-clauses.",
    "structure": "If + present simple, will + base verb",
    "questions": [
      { "question": "If she ____ hard, she will succeed.", "options": ["studies", "will study", "studied", "studying"], "answer": 0 }
    ]
  },
  {
    "id": "I-002",
    "level": "intermediate",
    "category": "conditionals",
    "name": "Second Conditional",
    "xpReward": 45,
    "difficulty": 4,
    "explanation": "Used for unreal or hypothetical present/future situations.",
    "structure": "If + past simple, would + base verb",
    "questions": [
      { "question": "If I ____ you, I would apologize.", "options": ["were", "was", "am", "be"], "answer": 0 }
    ]
  },
  {
    "id": "I-006",
    "level": "intermediate",
    "category": "conditionals",
    "xpReward": 50,
    "difficulty": 4,
    "name": "Third Conditional",
    "explanation": "Used for unreal situations in the past (regret or imagination).",
    "structure": "If + had + past participle, would have + past participle",
    "questions": [
      { "question": "If she ____ harder, she would have won.", "options": ["had tried", "would try", "tries", "has tried"], "answer": 0 }
    ]
  },
  {
    "id": "I-007",
    "level": "intermediate",
    "category": "conditionals",
    "name": "Mixed Conditionals",
    "xpReward": 55,
    "difficulty": 5,
    "explanation": "Mixed conditionals combine different time frames (past cause + present result).",
    "structure": "If + had + past participle, would + base verb",
    "questions": [
      { "question": "If she had studied medicine, she ____ a doctor now.", "options": ["would be", "would have been", "is", "was"], "answer": 0 }
    ]
  },
  {
    "id": "I-013",
    "level": "intermediate",
    "category": "mood",
    "name": "Subjunctive Mood",
    "xpReward": 55,
    "difficulty": 5,
    "explanation": "Subjunctive expresses wishes, demands, or hypothetical situations. Use 'were' for all subjects.",
    "structure": "If I were... | It is important that he be...",
    "questions": [
      { "question": "If I ____ you, I would leave.", "options": ["were", "was", "am", "be"], "answer": 0 }
    ]
  },
  {
    "id": "I-014",
    "level": "intermediate",
    "category": "inversion",
    "name": "Inversion after Negative Adverbs",
    "xpReward": 55,
    "difficulty": 5,
    "explanation": "After negative adverbs (Never, Rarely), we invert subject and auxiliary.",
    "structure": "Never + auxiliary + subject + verb",
    "questions": [
      { "question": "Rarely ____ he arrive on time.", "options": ["does", "is", "has", "was"], "answer": 0 }
    ]
  }
]

